period_tracker/__init__.py
period_tracker/__main__.py
simple_period_tracker-0.1.2.dist-info/METADATA
simple_period_tracker-0.1.2.dist-info/WHEEL
simple_period_tracker-0.1.2.dist-info/entry_points.txt
simple_period_tracker-0.1.2.dist-info/licenses/LICENSE
simple_period_tracker-0.1.2.dist-info/RECORD
