Metadata-Version: 2.4
Name: simple-period-tracker
Version: 0.1.2
Summary: A simple, command-line period tracker with statistical analysis and prediction.
License-Expression: MIT
License-File: LICENSE
Author: aufildelanuit
Author-email: yohann.opolka@gmail.com
Requires-Python: >=3.8
Classifier: Programming Language :: Python :: 3
Classifier: Programming Language :: Python :: 3.8
Classifier: Programming Language :: Python :: 3.9
Classifier: Programming Language :: Python :: 3.10
Classifier: Programming Language :: Python :: 3.11
Classifier: Programming Language :: Python :: 3.12
Classifier: Programming Language :: Python :: 3.13
Classifier: Programming Language :: Python :: 3.14
Provides-Extra: full
Requires-Dist: matplotlib ; extra == "full"
Requires-Dist: numpy ; extra == "full"
Requires-Dist: pandas ; extra == "full"
Requires-Dist: scipy ; extra == "full"
